dtpybucket/__init__.py
dtpybucket/bucket.py
dtpybucket-1.0.0.dist-info/METADATA
dtpybucket-1.0.0.dist-info/WHEEL
dtpybucket-1.0.0.dist-info/RECORD
