Metadata-Version: 2.3
Name: dtpybucket
Version: 1.0.0
Summary: A package to improved bucket and s3 compatible system library to have better development experience.
License: MIT
Author: Reza Shirazi
Author-email: reza@datgate.com
Requires-Python: >=3.11.9,<3.12.0
Classifier: License :: OSI Approved :: MIT License
Classifier: Programming Language :: Python :: 3
Requires-Dist: boto3 (>=1.37.19,<1.38.0)
Requires-Dist: botocore (>=1.37.19,<1.38.0)
Requires-Dist: dtpyutils (>=1.0.0,<1.1.0)
